MANIFEST.in
README.md
setup.py
chembl_clippy/__init__.py
chembl_clippy/clippy_all.py
chembl_clippy/settings.py
chembl_clippy/singleton.py
chembl_clippy.egg-info/PKG-INFO
chembl_clippy.egg-info/SOURCES.txt
chembl_clippy.egg-info/dependency_links.txt
chembl_clippy.egg-info/not-zip-safe
chembl_clippy.egg-info/requires.txt
chembl_clippy.egg-info/top_level.txt
chembl_clippy/art/clipper.icns
chembl_clippy/art/clipper.ico
chembl_clippy/art/exit.png