Metadata-Version: 1.1
Name: chembl-clippy
Version: 0.1.5
Summary: A cross-platform chemical structure rendering desktop app.
Home-page: https://www.ebi.ac.uk/chembl/
Author: George Papadatos
Author-email: georgep@ebi.ac.uk
License: MIT
Platform: UNKNOWN
Classifier: Development Status :: 2 - Pre-Alpha
Classifier: Environment :: MacOS X
Classifier: Environment :: Win32 (MS Windows)
Classifier: Environment :: X11 Applications
Classifier: Intended Audience :: Science/Research
Classifier: License :: OSI Approved :: MIT License
Classifier: Operating System :: Microsoft :: Windows
Classifier: Operating System :: MacOS
Classifier: Operating System :: POSIX :: Linux
Classifier: Programming Language :: Python :: 2.7
Classifier: Topic :: Scientific/Engineering :: Chemistry
